vpnconf/__init__.py
vpnconf/__main__.py
vpnconf-0.0.2.dist-info/LICENSE
vpnconf-0.0.2.dist-info/METADATA
vpnconf-0.0.2.dist-info/WHEEL
vpnconf-0.0.2.dist-info/entry_points.txt
vpnconf-0.0.2.dist-info/top_level.txt
vpnconf-0.0.2.dist-info/RECORD
